ml_track_tool/OpenSheet.py
ml_track_tool/__init__.py
ml_track_tool/flask_app.py
ml_track_tool/logo.jpg
ml_track_tool/plotly_.py
ml_track_tool/summary_plots.py
ml_track_tool/utils.py
ml_track_tool/templates/experiment_page.html
ml_track_tool/templates/myhtml.html
ml_track_tool/templates/summary.html
ml_track_tool/templates/visualization.html
MlTrackTool-0.0.19.dist-info/LICENSE
MlTrackTool-0.0.19.dist-info/METADATA
MlTrackTool-0.0.19.dist-info/WHEEL
MlTrackTool-0.0.19.dist-info/top_level.txt
MlTrackTool-0.0.19.dist-info/RECORD
