Metadata-Version: 2.1
Name: MlTrackTool
Version: 0.0.19
Summary: Documetation and Ml tracking tool using jupyter extensions
Home-page: https://github.com/anesh-ml/Document-and-ML-track-tool
Author: Anesh
Author-email: analytics955@gmail.com
License: UNKNOWN
Keywords: python,Machine learning,MLops,ML tracking system
Platform: UNKNOWN
Classifier: Development Status :: 1 - Planning
Classifier: Intended Audience :: Developers
Classifier: Programming Language :: Python :: 3
Classifier: Operating System :: Unix
Classifier: Operating System :: MacOS :: MacOS X
Classifier: Operating System :: Microsoft :: Windows
Requires-Python: >=3.7
License-File: LICENSE
Requires-Dist: ipysheet
Requires-Dist: scikit-plot
Requires-Dist: lime
Requires-Dist: Shapely
Requires-Dist: plotly
Requires-Dist: flask
Requires-Dist: jinja2
Requires-Dist: psutil
Requires-Dist: xlwt
Requires-Dist: imagesize
